offspot_config/__init__.py
offspot_config/builder.py
offspot_config/catalog.json
offspot_config/catalog.py
offspot_config/constants.py
offspot_config/file.py
offspot_config/oci_images.py
offspot_config/packages.py
offspot_config/zim.py
offspot_config/branding/horizontal-logo-dark.png
offspot_config/branding/horizontal-logo-light.png
offspot_config/branding/horizontal-logo.svg
offspot_config/branding/square-logo-dark.png
offspot_config/branding/square-logo-light.png
offspot_config/branding/square-logo.svg
offspot_config/inputs/__init__.py
offspot_config/inputs/base.py
offspot_config/inputs/checksum.py
offspot_config/inputs/file.py
offspot_config/inputs/mainconfig.py
offspot_config/inputs/oci.py
offspot_config/inputs/output.py
offspot_config/inputs/str.py
offspot_config/inputs/ways.py
offspot_config/utils/__init__.py
offspot_config/utils/dashboard.py
offspot_config/utils/download.py
offspot_config/utils/misc.py
offspot_config/utils/sizes.py
offspot_config/utils/yaml.py
offspot_runtime/__about__.py
offspot_runtime/__init__.py
offspot_runtime/ap.py
offspot_runtime/checks.py
offspot_runtime/configlib.py
offspot_runtime/containers.py
offspot_runtime/dnsmasqspoof.py
offspot_runtime/ethernet.py
offspot_runtime/firmware.py
offspot_runtime/fromfile.py
offspot_runtime/hostname.py
offspot_runtime/timezone.py
offspot_config-2.9.2.dist-info/METADATA
offspot_config-2.9.2.dist-info/WHEEL
offspot_config-2.9.2.dist-info/entry_points.txt
offspot_config-2.9.2.dist-info/licenses/LICENSE
offspot_config-2.9.2.dist-info/RECORD
