Metadata-Version: 2.4
Name: offspot-config
Version: 2.9.2
Summary: Offspot Config helpers
Project-URL: Homepage, https://github.com/offspot/offspot-config
Project-URL: Donate, https://www.kiwix.org/en/support-us/
Author-email: Kiwix <dev@kiwix.org>
License: GPL-3.0-or-later
License-File: LICENSE
Keywords: offspot
Classifier: License :: OSI Approved :: GNU General Public License v3 or later (GPLv3+)
Classifier: Operating System :: POSIX
Classifier: Programming Language :: Python :: 3
Classifier: Programming Language :: Python :: 3.11
Classifier: Programming Language :: Python :: 3.12
Classifier: Programming Language :: Python :: 3.13
Requires-Python: >=3.11
Requires-Dist: attrs<23.2,>=23.1.0
Requires-Dist: docker-export[visual]<2.0,>=1.0.0
Requires-Dist: humanfriendly>=10.0
Requires-Dist: iso3166==2.1.1
Requires-Dist: pathvalidate<4.0,>=3.0.0
Requires-Dist: pyyaml==6.0.1
Requires-Dist: requests<3,>=2.31.0
Requires-Dist: typeguard>=4.1.5
Requires-Dist: urllib3<3.0,>=2.0.0
Requires-Dist: xmltodict<0.14,>=0.13.0
Provides-Extra: check
Requires-Dist: pyright==1.1.363; extra == 'check'
Provides-Extra: dev
Requires-Dist: black==24.4.2; extra == 'dev'
Requires-Dist: coverage==7.5.1; extra == 'dev'
Requires-Dist: invoke==2.2.0; extra == 'dev'
Requires-Dist: ipython==8.24.0; extra == 'dev'
Requires-Dist: pre-commit==3.7.1; extra == 'dev'
Requires-Dist: pyright==1.1.363; extra == 'dev'
Requires-Dist: pytest==8.2.1; extra == 'dev'
Requires-Dist: ruff==0.4.4; extra == 'dev'
Provides-Extra: lint
Requires-Dist: black==24.4.2; extra == 'lint'
Requires-Dist: ruff==0.4.4; extra == 'lint'
Provides-Extra: scripts
Requires-Dist: invoke==2.2.0; extra == 'scripts'
Provides-Extra: test
Requires-Dist: coverage==7.5.1; extra == 'test'
Requires-Dist: pytest==8.2.1; extra == 'test'
